{
    "template1": {
        "text": "What is the perimeter of an iscoceles triangle of side length {param1} and hypotenuse {param2}?",
        "num_params": 2
    },
    "template2": {
        "text": "What is the perimeter of a triangle with side lengths {param1}, {param2}, and {param3}?",
        "num_params": 3
    },
    "template3": {
        "text": "What is the perimeter of an equilateral triangle with side length {param1}?",
        "num_params": 1
    },
    "template4": {
        "text": "If we have a triangle with side lengths {param1}, {param2}, and {param3}. What is its perimeter?",
        "num_params": 3
    },
    "template5": {
        "text": "If we have an iscoceles triangle with side length {param1} and hypotenuse {param2}. What is its perimeter?",
        "num_params": 2
    },
    "template6": {
        "text": "If we have an equilateral triangle with side length {param2}. What is its perimeter?",
        "num_params": 1
    }
}
